{
	"id": "warotickets-prod-env",
	"name": "WaRo Tickets - Production",
	"values": [
		{
			"key": "BASE_URL",
			"value": "https://api.warotickets.com",
			"type": "default",
			"enabled": true
		},
		{
			"key": "USER_EMAIL",
			"value": "",
			"type": "default",
			"enabled": true
		},
		{
			"key": "EVENT_ID",
			"value": "",
			"type": "default",
			"enabled": true
		},
		{
			"key": "EVENT_SLUG",
			"value": "",
			"type": "default",
			"enabled": true
		},
		{
			"key": "AREA_ID",
			"value": "",
			"type": "default",
			"enabled": true
		},
		{
			"key": "UNIT_ID",
			"value": "",
			"type": "default",
			"enabled": true
		},
		{
			"key": "RESERVATION_ID",
			"value": "",
			"type": "default",
			"enabled": true
		},
		{
			"key": "RESERVATION_UNIT_ID",
			"value": "",
			"type": "default",
			"enabled": true
		},
		{
			"key": "PAYMENT_ID",
			"value": "",
			"type": "default",
			"enabled": true
		},
		{
			"key": "STAGE_ID",
			"value": "",
			"type": "default",
			"enabled": true
		},
		{
			"key": "PROMOTION_ID",
			"value": "",
			"type": "default",
			"enabled": true
		},
		{
			"key": "IMAGE_ID",
			"value": "",
			"type": "default",
			"enabled": true
		},
		{
			"key": "TRANSFER_TOKEN",
			"value": "",
			"type": "default",
			"enabled": true
		},
		{
			"key": "SESSION_TOKEN",
			"value": "",
			"type": "secret",
			"enabled": true
		},
		{
			"key": "WOMPI_CHECKSUM",
			"value": "",
			"type": "default",
			"enabled": true
		}
	],
	"_postman_variable_scope": "environment"
}
